{
  "miniprogramRoot": "dist/",
  "projectname": "yngdieng",
  "description": "福州话电子词典",
  "appid": "wx102d8ec4d1bafaaf",
  "setting": {
    "urlCheck": true,
    "es6": false,
    "enhance": false,
    "postcss": false,
    "preloadBackgroundData": false,
    "minified": false,
    "newFeature": true,
    "coverView": true,
    "nodeModules": false,
    "autoAudits": false,
    "showShadowRootInWxmlPanel": true,
    "scopeDataCheck": false,
    "uglifyFileName": false,
    "checkInvalidKey": true,
    "checkSiteMap": true,
    "uploadWithSourceMap": true,
    "compileHotReLoad": false,
    "useMultiFrameRuntime": false,
    "useApiHook": true,
    "babelSetting": {
      "ignore": [],
      "disablePlugins": [],
      "outputPath": ""
    },
    "useIsolateContext": true,
    "useCompilerModule": true,
    "userConfirmedUseCompilerModuleSwitch": false,
    "packNpmManually": false,
    "packNpmRelationList": []
  },
  "compileType": "miniprogram",
  "simulatorType": "wechat",
  "simulatorPluginLibVersion": {},
  "cloudfunctionTemplateRoot": "cloudfunctionTemplate",
  "condition": {
    "search": {
      "current": -1,
      "list": []
    },
    "conversation": {
      "current": -1,
      "list": []
    },
    "plugin": {
      "current": -1,
      "list": []
    },
    "game": {
      "list": []
    },
    "gamePlugin": {
      "current": -1,
      "list": []
    },
    "miniprogram": {
      "current": -1,
      "list": [
        {
          "id": 0,
          "name": "pages/search/search",
          "pathName": "pages/search/search",
          "query": "word=test",
          "scene": null
        },
        {
          "id": 1,
          "name": "pages/wordDetail/wordDetail",
          "pathName": "pages/wordDetail/wordDetail",
          "query": "id=1",
          "scene": null
        },
        {
          "id": 2,
          "name": "pages/collectionDetail/collectionDetail",
          "pathName": "pages/collectionDetail/collectionDetail",
          "query": "id=lung-nung-dieng",
          "scene": null
        }
      ]
    }
  }
}
